Metadata-Version: 1.1
Name: keyauth-api
Version: 0.0.3
Summary: A wrapper for the authentication service keyauth
Home-page: UNKNOWN
Author: expresso
Author-email: unkegdiscord@gmail.com
License: MIT
Keywords: wrapper,authentication,api,keyauth
Platform: UNKNOWN
Classifier: Development Status :: 5 - Production/Stable
Classifier: Intended Audience :: Education
Classifier: Operating System :: Microsoft :: Windows :: Windows 10
Classifier: License :: OSI Approved :: MIT License
Classifier: Programming Language :: Python :: 3
